<annotation>
  <folder>Training Images</folder>
  <filename>ivjz9y</filename>
  <path>C:\Users\Chintan\Desktop\Training Images\ivjz9y.jpg</path>
  <source>
    <database>Unknown</database>
  </source>
  <size>
    <width>638</width>
    <height>351</height>
    <depth>3</depth>
  </size>
  <segmented>0</segmented>
  <object>
    <name>player</name>
    <pose>Unspecified</pose>
    <truncated>0</truncated>
    <difficult>0</difficult>
    <bndbox>
      <xmin>293</xmin>
      <ymin>99</ymin>
      <xmax>304</xmax>
      <ymax>130</ymax>
    </bndbox>
  </object>
  <object>
    <name>player</name>
    <pose>Unspecified</pose>
    <truncated>0</truncated>
    <difficult>0</difficult>
    <bndbox>
      <xmin>113</xmin>
      <ymin>205</ymin>
      <xmax>128</xmax>
      <ymax>242</ymax>
    </bndbox>
  </object>
  <object>
    <name>player</name>
    <pose>Unspecified</pose>
    <truncated>0</truncated>
    <difficult>0</difficult>
    <bndbox>
      <xmin>122</xmin>
      <ymin>134</ymin>
      <xmax>137</xmax>
      <ymax>167</ymax>
    </bndbox>
  </object>
  <object>
    <name>player</name>
    <pose>Unspecified</pose>
    <truncated>0</truncated>
    <difficult>0</difficult>
    <bndbox>
      <xmin>43</xmin>
      <ymin>59</ymin>
      <xmax>56</xmax>
      <ymax>88</ymax>
    </bndbox>
  </object>
  <object>
    <name>player</name>
    <pose>Unspecified</pose>
    <truncated>0</truncated>
    <difficult>0</difficult>
    <bndbox>
      <xmin>275</xmin>
      <ymin>28</ymin>
      <xmax>286</xmax>
      <ymax>53</ymax>
    </bndbox>
  </object>
  <object>
    <name>player</name>
    <pose>Unspecified</pose>
    <truncated>0</truncated>
    <difficult>0</difficult>
    <bndbox>
      <xmin>337</xmin>
      <ymin>24</ymin>
      <xmax>347</xmax>
      <ymax>52</ymax>
    </bndbox>
  </object>
  <object>
    <name>player</name>
    <pose>Unspecified</pose>
    <truncated>0</truncated>
    <difficult>0</difficult>
    <bndbox>
      <xmin>270</xmin>
      <ymin>251</ymin>
      <xmax>287</xmax>
      <ymax>289</ymax>
    </bndbox>
  </object>
  <object>
    <name>player</name>
    <pose>Unspecified</pose>
    <truncated>0</truncated>
    <difficult>0</difficult>
    <bndbox>
      <xmin>509</xmin>
      <ymin>207</ymin>
      <xmax>519</xmax>
      <ymax>246</ymax>
    </bndbox>
  </object>
  <object>
    <name>player</name>
    <pose>Unspecified</pose>
    <truncated>0</truncated>
    <difficult>0</difficult>
    <bndbox>
      <xmin>497</xmin>
      <ymin>132</ymin>
      <xmax>505</xmax>
      <ymax>165</ymax>
    </bndbox>
  </object>
  <object>
    <name>player</name>
    <pose>Unspecified</pose>
    <truncated>0</truncated>
    <difficult>0</difficult>
    <bndbox>
      <xmin>377</xmin>
      <ymin>95</ymin>
      <xmax>387</xmax>
      <ymax>127</ymax>
    </bndbox>
  </object>
  <object>
    <name>player</name>
    <pose>Unspecified</pose>
    <truncated>0</truncated>
    <difficult>0</difficult>
    <bndbox>
      <xmin>571</xmin>
      <ymin>65</ymin>
      <xmax>581</xmax>
      <ymax>92</ymax>
    </bndbox>
  </object>
  <object>
    <name>player</name>
    <pose>Unspecified</pose>
    <truncated>0</truncated>
    <difficult>0</difficult>
    <bndbox>
      <xmin>307</xmin>
      <ymin>172</ymin>
      <xmax>318</xmax>
      <ymax>208</ymax>
    </bndbox>
  </object>
  <object>
    <name>player</name>
    <pose>Unspecified</pose>
    <truncated>0</truncated>
    <difficult>0</difficult>
    <bndbox>
      <xmin>320</xmin>
      <ymin>158</ymin>
      <xmax>323</xmax>
      <ymax>188</ymax>
    </bndbox>
  </object>
</annotation>
